augvid/__init__.py
augvid/_utils.py
augvid/layers.py
augvid-0.0.1.dist-info/licenses/LICENSE
augvid-0.0.1.dist-info/METADATA
augvid-0.0.1.dist-info/WHEEL
augvid-0.0.1.dist-info/top_level.txt
augvid-0.0.1.dist-info/RECORD
